<?xml version="1.0" encoding="UTF-8" standalone="yes"?>
<KNT_TROUBLE>
	<KOKAI_REV_NBR>0</KOKAI_REV_NBR>
	<TROUBLE_ID>13367</TROUBLE_ID>
	<KANRYO_FLG><![CDATA[0]]></KANRYO_FLG>
	<UPDATE_DATE><![CDATA[2021/09/11 10:31:40]]></UPDATE_DATE>
	<JOHO_KUBUN_CODE><![CDATA[S]]></JOHO_KUBUN_CODE>
	<JOHO_KUBUN_CODE_NAME><![CDATA[その他情報]]></JOHO_KUBUN_CODE_NAME>
	<RO_TYPE_CODE><![CDATA[B]]></RO_TYPE_CODE>
	<RO_TYPE_CODE_NAME><![CDATA[BWR]]></RO_TYPE_CODE_NAME>
	<SUIHEI_KENTO_CODE><![CDATA[X]]></SUIHEI_KENTO_CODE>
	<SUIHEI_KENTO_CODE_NAME><![CDATA[対象外]]></SUIHEI_KENTO_CODE_NAME>
	<ATTACH_ID>101598</ATTACH_ID>
	<CREATE_DATE><![CDATA[2021/09/11 10:31:00]]></CREATE_DATE>
	<HASSEI_NJ><![CDATA[202109061450]]></HASSEI_NJ>
	<HASSEIJI_JOKYO_TXT><![CDATA[2021年9月6日、3号機軽油タンクエリア屋外において消火設備の点検作業に従事していた協力企業作業員が体調不良を訴えたことから、同日、午後2時50分に業務車で病院に搬送された。
病院での診察の結果、「熱中症疑いおよび脱水」と診断され、点滴の処置を受けたのちに帰宅している。
当該の協力企業作業員は、熱中症対策としてこまめな休憩や水分補給を行っていたが、本件を踏まえ、当社社員および協力企業の方々へ業務開始前の体調確認や、休憩、適度な水分および塩分等のミネラル補給を心がけるよう、あらためて注意喚起を行う。]]></HASSEIJI_JOKYO_TXT>
	<PLANT_CODE><![CDATA[tyokk]]></PLANT_CODE>
	<REPORT_NO><![CDATA[2021-東京-S019]]></REPORT_NO>
	<COMPANY_CODE><![CDATA[tyo]]></COMPANY_CODE>
	<HOKOKUSHO_JOTAI_CODE><![CDATA[02]]></HOKOKUSHO_JOTAI_CODE>
	<HOKOKUSHO_JOTAI_CODE_NAME><![CDATA[最終報告]]></HOKOKUSHO_JOTAI_CODE_NAME>
	<TITLE_NAME><![CDATA[軽油タンクエリア（屋外）における体調不良者（熱中症疑い、脱水）の発生について]]></TITLE_NAME>
	<UNITS><![CDATA[3]]></UNITS>
	<ATTACH_UMU_CODE><![CDATA[1]]></ATTACH_UMU_CODE>
	<ATTACH_UMU_CODE_NAME><![CDATA[あり]]></ATTACH_UMU_CODE_NAME>
	<KOKAI_FLG><![CDATA[1]]></KOKAI_FLG>
	<FIRST_KOKAI_DATE><![CDATA[2021/09/11 10:31:40]]></FIRST_KOKAI_DATE>
	<COM_COMPANY>
		<COMPANY_NAME><![CDATA[東京電力]]></COMPANY_NAME>
		<COMPANY_SHORT_NAME><![CDATA[東京]]></COMPANY_SHORT_NAME>
		<COMPANY_FULL_NAME><![CDATA[東京電力株式会社]]></COMPANY_FULL_NAME>
		<CREATE_DATE><![CDATA[2010/05/31 00:00:00]]></CREATE_DATE>
		<COMPANY_CODE><![CDATA[tyo]]></COMPANY_CODE>
		<CREATE_USER_CODE><![CDATA[mainte01]]></CREATE_USER_CODE>
		<SORT_NO>30</SORT_NO>
		<SYSTEM_CODE><![CDATA[KN]]></SYSTEM_CODE>
		<D_RO_TYPE_CODE><![CDATA[B]]></D_RO_TYPE_CODE>
	</COM_COMPANY>
	<KNM_PLANT>
		<COMPANY_CODE><![CDATA[tyo]]></COMPANY_CODE>
		<CREATE_USER_CODE><![CDATA[mainte01]]></CREATE_USER_CODE>
		<PLANT_RYAKU_NAME><![CDATA[柏崎刈羽]]></PLANT_RYAKU_NAME>
		<SORT_NO>6</SORT_NO>
		<PLANT_CODE><![CDATA[tyokk]]></PLANT_CODE>
		<D_RO_TYPE_CODE><![CDATA[B]]></D_RO_TYPE_CODE>
		<PLANT_NAME><![CDATA[柏崎刈羽発電所]]></PLANT_NAME>
		<CREATE_DATE><![CDATA[2010/05/31 00:00:00]]></CREATE_DATE>
	</KNM_PLANT>
</KNT_TROUBLE>
