<?xml version="1.0" encoding="UTF-8" standalone="yes"?>
<KNT_TROUBLE>
	<KOKAI_REV_NBR>1</KOKAI_REV_NBR>
	<TROUBLE_ID>11957</TROUBLE_ID>
	<KANRYO_FLG><![CDATA[0]]></KANRYO_FLG>
	<UPDATE_DATE><![CDATA[2015/12/21 22:22:15]]></UPDATE_DATE>
	<JOHO_KUBUN_CODE><![CDATA[S]]></JOHO_KUBUN_CODE>
	<JOHO_KUBUN_CODE_NAME><![CDATA[その他情報]]></JOHO_KUBUN_CODE_NAME>
	<RO_TYPE_CODE><![CDATA[B]]></RO_TYPE_CODE>
	<RO_TYPE_CODE_NAME><![CDATA[BWR]]></RO_TYPE_CODE_NAME>
	<SUIHEI_KENTO_CODE><![CDATA[X]]></SUIHEI_KENTO_CODE>
	<SUIHEI_KENTO_CODE_NAME><![CDATA[対象外]]></SUIHEI_KENTO_CODE_NAME>
	<ATTACH_ID>58948</ATTACH_ID>
	<CREATE_DATE><![CDATA[2014/03/16 10:37:44]]></CREATE_DATE>
	<HASSEI_NJ><![CDATA[201402111220]]></HASSEI_NJ>
	<KOKAI_UPDATE_DATE><![CDATA[2015/12/21 22:22:15]]></KOKAI_UPDATE_DATE>
	<HASSEIJI_JOKYO_TXT><![CDATA[２月11日午後０時20分頃、汚染水タンクパトロールにおいてＨ４タンクエリア堰内の床コンクリート部に、目視で確認できる範囲で長さ1.5ｍ程度の亀裂を協力企業作業員が発見。２月８日（降雪前）の当該堰内水位は０ｃｍであることを確認しているが、堰内には積雪があり、亀裂箇所から水がはけることを確認したことから、念のため当該堰内水の分析を実施。また、同日午後３時35分頃、Ｈ４東タンクエリアの堰内床コンクリート部に８ｍ程度の亀裂があることを協力企業作業員が確認。亀裂部付近に水はなく、亀裂部への水の流入は確認されていない。堰内の水の分析結果については、以下のとおり。
＜Ｈ４タンクエリア：午後３時28分採水＞
・セシウム134	：検出限界値未満（検出限界値：12 Bq/L）
・セシウム137	：検出限界値未満（検出限界値：17 Bq/L）
・ストロンチウム90	：17 Bq/L
＜Ｈ４東タンクエリア：午後４時27分採水＞
・セシウム134　　	：13 Bq/L
・セシウム137　　	：45 Bq/L
・ストロンチウム90	：2,100 Bq/L
同日、Ｈ４およびＨ４東タンクエリア堰内床コンクリート部の亀裂について、エポキシ系塗料による補修が終了。Ｈ４およびＨ４東タンクエリア堰内の当該亀裂部付近に水はなく、亀裂への水の流入は確認されなかった。また、Ｈ４タンクエリアの亀裂について亀裂周辺の雪を取り除いて確認したところ、亀裂の長さは約12ｍであることを確認。また、Ｈ４およびＨ４東タンクエリアの各タンクの目視点検において漏えい等は確認できず、汚染水タンク水位計による常時監視（警報監視）においても異常はなかった。

なお、Ｈ４エリア周辺地下水（Ｆ-1：当該タンクエリア上流部、Ｅ-11及びＥ-12：当該タンクエリア下流部）の分析結果については、以下の通り。
＜Ｅ-11(当該タンクエリア下流部)：２月12日採水＞全ベータ：25 Bq/L
＜Ｅ-12(当該タンクエリア下流部)：２月12日採水＞全ベータ：検出限界値未満（検出限界値：17 Bq/L）
＜Ｆ-１(当該タンクエリア上流部)：２月11日採水＞全ベータ：検出限界値未満（検出限界値：17 Bq/L）、トリチウム：660 Bq/L
当該タンクエリア周辺の地下水の上流部、下流部共に前回と比較して有意な変動はない。]]></HASSEIJI_JOKYO_TXT>
	<PLANT_CODE><![CDATA[tyo1f]]></PLANT_CODE>
	<REPORT_NO><![CDATA[2013-東京-S104]]></REPORT_NO>
	<COMPANY_CODE><![CDATA[tyo]]></COMPANY_CODE>
	<HOKOKUSHO_JOTAI_CODE><![CDATA[02]]></HOKOKUSHO_JOTAI_CODE>
	<HOKOKUSHO_JOTAI_CODE_NAME><![CDATA[最終報告]]></HOKOKUSHO_JOTAI_CODE_NAME>
	<TITLE_NAME><![CDATA[福島第一原子力発電所　H4およびH4東タンクエリアにおける基礎コンクリートのひび割れについて]]></TITLE_NAME>
	<ATTACH_UMU_CODE><![CDATA[1]]></ATTACH_UMU_CODE>
	<ATTACH_UMU_CODE_NAME><![CDATA[あり]]></ATTACH_UMU_CODE_NAME>
	<KOKAI_FLG><![CDATA[1]]></KOKAI_FLG>
	<FIRST_KOKAI_DATE><![CDATA[2014/03/26 17:21:00]]></FIRST_KOKAI_DATE>
	<COM_COMPANY>
		<COMPANY_NAME><![CDATA[東京電力]]></COMPANY_NAME>
		<COMPANY_SHORT_NAME><![CDATA[東京]]></COMPANY_SHORT_NAME>
		<COMPANY_FULL_NAME><![CDATA[東京電力株式会社]]></COMPANY_FULL_NAME>
		<CREATE_DATE><![CDATA[2010/05/31 00:00:00]]></CREATE_DATE>
		<COMPANY_CODE><![CDATA[tyo]]></COMPANY_CODE>
		<CREATE_USER_CODE><![CDATA[mainte01]]></CREATE_USER_CODE>
		<SORT_NO>30</SORT_NO>
		<SYSTEM_CODE><![CDATA[KN]]></SYSTEM_CODE>
		<D_RO_TYPE_CODE><![CDATA[B]]></D_RO_TYPE_CODE>
	</COM_COMPANY>
	<KNM_PLANT>
		<COMPANY_CODE><![CDATA[tyo]]></COMPANY_CODE>
		<CREATE_USER_CODE><![CDATA[mainte01]]></CREATE_USER_CODE>
		<PLANT_RYAKU_NAME><![CDATA[福島第一]]></PLANT_RYAKU_NAME>
		<SORT_NO>4</SORT_NO>
		<PLANT_CODE><![CDATA[tyo1f]]></PLANT_CODE>
		<D_RO_TYPE_CODE><![CDATA[B]]></D_RO_TYPE_CODE>
		<PLANT_NAME><![CDATA[福島第一発電所]]></PLANT_NAME>
		<CREATE_DATE><![CDATA[2010/05/31 00:00:00]]></CREATE_DATE>
	</KNM_PLANT>
</KNT_TROUBLE>
