<?xml version="1.0" encoding="UTF-8" standalone="yes"?>
<KNT_TROUBLE>
	<KOKAI_REV_NBR>0</KOKAI_REV_NBR>
	<TROUBLE_ID>11430</TROUBLE_ID>
	<KANRYO_FLG><![CDATA[0]]></KANRYO_FLG>
	<UPDATE_DATE><![CDATA[2011/12/22 12:28:34]]></UPDATE_DATE>
	<JOHO_KUBUN_CODE><![CDATA[S]]></JOHO_KUBUN_CODE>
	<JOHO_KUBUN_CODE_NAME><![CDATA[その他情報]]></JOHO_KUBUN_CODE_NAME>
	<RO_TYPE_CODE><![CDATA[B]]></RO_TYPE_CODE>
	<RO_TYPE_CODE_NAME><![CDATA[BWR]]></RO_TYPE_CODE_NAME>
	<SUIHEI_KENTO_CODE><![CDATA[X]]></SUIHEI_KENTO_CODE>
	<SUIHEI_KENTO_CODE_NAME><![CDATA[対象外]]></SUIHEI_KENTO_CODE_NAME>
	<ATTACH_ID>26507</ATTACH_ID>
	<CREATE_DATE><![CDATA[2011/12/22 11:48:11]]></CREATE_DATE>
	<HASSEI_NJ><![CDATA[20110906]]></HASSEI_NJ>
	<HASSEIJI_JOKYO_TXT><![CDATA[ 当社は，平成２３年７月２２日付けの原子力安全・保安院からの指示文書「東京電力株式会社福島第一原子力発電所における事故を踏まえた既設の発電用原子炉施設の安全性に関する総合評価の実施について（指示）（平成２３・０７・２０原院第１号）」に基づき，評価を実施するための事前準備の一環として，「平成２３年福島第一・第二原子力発電所事故を踏まえた緊急安全対策に係る実施状況報告書」（平成２３年４月２２日提出）の評価内容等を確認していたところ，敦賀発電所２号機の定検時取出燃料の冷却期間が誤った記載であることを９月６日に確認した。
 このため，東北地方太平洋沖地震が発生した３月１１日以降に，国からの指示に基づき当社が提出した緊急安全対策等の報告書について，同様な記載誤りがないか調査を行った結果，以下の報告書に記載誤りのあることを確認した。

○平成２３年福島第一・第二原子力発電所事故を踏まえた緊急安全対策に係る実施状況報告書（東海第二発電所，敦賀発電所）（平成２３年４月２２日提出）
○平成２３年福島第一原子力発電所事故を踏まえたシビアアクシデントへの対応に関する措置に係る実施状況報告書（平成２３年６月１４日提出）
○原子力発電所等の外部電源の信頼性確保に係る開閉所等の地震対策について（報告）（平成２３年７月７日提出）

 記載誤りが確認された報告書については，訂正，または補正を行うとともに，９月１５日にその内容を国に報告した。
 また，同日，原子力安全・保安院より，指示文書「緊急安全対策等の報告書の誤りを踏まえた対応について（指示）（平成２３・０９・１４原院第５号）」を受領し，国からの指示に基づき当社が提出した以下の報告書について，報告内容の誤りの有無を調査し，誤りがあった場合は，誤りが発生した原因の究明及び再発防止策の策定を行い，報告するよう指示を受けた。
 この指示を受けて，数値等の記載誤りに係る調査を実施し,９月２８日に原子力安全・保安院へ報告しました。
その後、原子力安全･保安院による確認・評価が実施されておりましたが、「調査結果報告書に記載された調査体制及び方法による十分な調査結果等が行われているとは認められない部分があった」として、１０月２６日、原子力安全・保安院より指示文書「緊急安全対策等の報告書における誤りの有無の再調査について（指示）」（平成２３・１０・２５原院第２号）を受領しました。
 これに基づき、対象報告書の再調査を行った結果、東海第二発電所の緊急時安全対策実施状況報告書に記載した復水貯蔵タンクの使用可能水量に誤りがあることを確認しました。今回の誤り修正後の数値で再評価を行い、原子炉及び使用済燃料プールへの必要な注水流量は確保されていることを確認しています。このため、記載誤りが確認されたことおよびその原因と再発防止対策について、原子力安全・保安院に報告するとともに、東海第二発電所の緊急安全対策実施状況報告書（訂正）を提出しました。
なお、その他の対象報告書については、記載に誤りはありませんでした。

○平成２３年３月３０日付け「平成２３年福島第一・第二原子力発電所事故を踏まえた他の発電所の緊急安全対策の実施について（指示）」（平成２３・０３・２８原第７号）
○平成２３年４月１５日付け「原子力発電所及び再処理施設の外部電源の信頼性確保について（指示）」（平成２３・０４・１５原院第３号）
○平成２３年６月７日付け「平成２３年福島第一原子力発電所事故を踏まえた他の原子力発電所におけるシビアアクシデントへの対応に関する措置の実施について（指示）」（平成２３・０６・０７原第２号）
○平成２３年６月７日付け「原子力発電所等の外部電源の信頼性確保に係る開閉所等の地震対策について（指示）」（平成２３・０６・０７原院第１号）
○平成２３年１０月２６日付け「緊急安全対策等の報告書における誤りの有無の再調査について（指示）」
（平成２３・１０・２５原院第２号）
]]></HASSEIJI_JOKYO_TXT>
	<PLANT_CODE><![CDATA[gentk]]></PLANT_CODE>
	<REPORT_NO><![CDATA[2011-原電-S002]]></REPORT_NO>
	<COMPANY_CODE><![CDATA[gen]]></COMPANY_CODE>
	<HOKOKUSHO_JOTAI_CODE><![CDATA[02]]></HOKOKUSHO_JOTAI_CODE>
	<HOKOKUSHO_JOTAI_CODE_NAME><![CDATA[最終報告]]></HOKOKUSHO_JOTAI_CODE_NAME>
	<TITLE_NAME><![CDATA[緊急安全対策等の報告書における記載誤りの調査結果]]></TITLE_NAME>
	<ATTACH_UMU_CODE><![CDATA[1]]></ATTACH_UMU_CODE>
	<ATTACH_UMU_CODE_NAME><![CDATA[あり]]></ATTACH_UMU_CODE_NAME>
	<KOKAI_FLG><![CDATA[1]]></KOKAI_FLG>
	<FIRST_KOKAI_DATE><![CDATA[2011/12/22 12:28:34]]></FIRST_KOKAI_DATE>
	<COM_COMPANY>
		<COMPANY_NAME><![CDATA[日本原子力発電]]></COMPANY_NAME>
		<COMPANY_SHORT_NAME><![CDATA[原電]]></COMPANY_SHORT_NAME>
		<COMPANY_FULL_NAME><![CDATA[日本原子力発電株式会社]]></COMPANY_FULL_NAME>
		<CREATE_DATE><![CDATA[2010/05/31 00:00:00]]></CREATE_DATE>
		<COMPANY_CODE><![CDATA[gen]]></COMPANY_CODE>
		<CREATE_USER_CODE><![CDATA[mainte01]]></CREATE_USER_CODE>
		<SORT_NO>100</SORT_NO>
		<SYSTEM_CODE><![CDATA[KN]]></SYSTEM_CODE>
		<D_RO_TYPE_CODE><![CDATA[B]]></D_RO_TYPE_CODE>
	</COM_COMPANY>
	<KNM_PLANT>
		<COMPANY_CODE><![CDATA[gen]]></COMPANY_CODE>
		<CREATE_USER_CODE><![CDATA[mainte01]]></CREATE_USER_CODE>
		<PLANT_RYAKU_NAME><![CDATA[東海第二]]></PLANT_RYAKU_NAME>
		<SORT_NO>17</SORT_NO>
		<PLANT_CODE><![CDATA[gentk]]></PLANT_CODE>
		<D_RO_TYPE_CODE><![CDATA[B]]></D_RO_TYPE_CODE>
		<PLANT_NAME><![CDATA[東海第二発電所]]></PLANT_NAME>
		<CREATE_DATE><![CDATA[2010/05/31 00:00:00]]></CREATE_DATE>
	</KNM_PLANT>
</KNT_TROUBLE>
