<?xml version="1.0" encoding="UTF-8" standalone="yes"?>
<KNT_TROUBLE>
	<KOKAI_REV_NBR>0</KOKAI_REV_NBR>
	<TROUBLE_ID>13432</TROUBLE_ID>
	<KANRYO_FLG><![CDATA[0]]></KANRYO_FLG>
	<UPDATE_DATE><![CDATA[2022/02/03 14:39:47]]></UPDATE_DATE>
	<JOHO_KUBUN_CODE><![CDATA[S]]></JOHO_KUBUN_CODE>
	<JOHO_KUBUN_CODE_NAME><![CDATA[その他情報]]></JOHO_KUBUN_CODE_NAME>
	<RO_TYPE_CODE><![CDATA[P]]></RO_TYPE_CODE>
	<RO_TYPE_CODE_NAME><![CDATA[PWR]]></RO_TYPE_CODE_NAME>
	<SUIHEI_KENTO_CODE><![CDATA[X]]></SUIHEI_KENTO_CODE>
	<SUIHEI_KENTO_CODE_NAME><![CDATA[対象外]]></SUIHEI_KENTO_CODE_NAME>
	<ATTACH_ID>104352</ATTACH_ID>
	<CREATE_DATE><![CDATA[2022/02/03 14:39:32]]></CREATE_DATE>
	<HASSEI_NJ><![CDATA[202201311743]]></HASSEI_NJ>
	<HASSEIJI_JOKYO_TXT><![CDATA[定期検査中の高浜発電所１、２号機のアスファルト固化建屋※１（管理区域）において、２０２２年１月３１日１７時４３分、火災報知器が発報したため、現場作業員が直ちに消火を行うとともに、当社社員が１７時４６分に１１９番通報を行った。

現場では、雑固体焼却設備セラミックフィルタ※２を収納している金属容器の内側で溶接補修を行っていたところ、溶接の熱が容器の外側に伝わり、外部を養生していたビニールシートが発火した。
発火を確認した現場作業員が、直ちに水噴霧器を用いて消火した。

その後、消防署員による現場確認が行われ、１８時４２分に鎮火が確認された。
なお、本件において負傷者は発生しておらず、環境への放射能の影響はない。また、容器本体ならびに周辺機器に影響はない。

作業状況等を確認したところ、容器内側の溶接補修前に耐火レンガ等を剥がし取って撤去する必要があったため、その際に発生する粉塵が飛散しないよう容器の外側にビニールシートで養生が行われていた。
また、溶接作業に当たって、耐火レンガ等の撤去作業完了後から作業当日までの間に作業責任者と作業員との間で行われた養生の状態についての相互確認が不十分であったため、溶接作業時には外すべきビニールシートが残った状態となったことが分かった。
このため、金属容器内部から溶接による熱が外側に伝わり、ビニールシートが発火したものと推定した。

対策として、作業責任者および火気監視員が作業前の確認を行うに当たっては、溶接面の裏面を含め、溶接による熱の影響を受ける範囲にシートやテープ等の可燃物がないことを自らが確認するよう社内ルールに明記する。
また、今回の事象を協力会社に周知し、火災防止の徹底について注意喚起した。

※１ 放射線管理区域で発生する液体廃棄物をアスファルトで固体化する装置と雑固体を焼却する装置を設置している建屋
※２ 焼却炉の排ガスから灰を除去するために設けているセラミック製（耐熱性を備えた）のフィルタ]]></HASSEIJI_JOKYO_TXT>
	<PLANT_CODE><![CDATA[knsth]]></PLANT_CODE>
	<REPORT_NO><![CDATA[2021-関西-S003]]></REPORT_NO>
	<COMPANY_CODE><![CDATA[kns]]></COMPANY_CODE>
	<HOKOKUSHO_JOTAI_CODE><![CDATA[02]]></HOKOKUSHO_JOTAI_CODE>
	<HOKOKUSHO_JOTAI_CODE_NAME><![CDATA[最終報告]]></HOKOKUSHO_JOTAI_CODE_NAME>
	<TITLE_NAME><![CDATA[高浜発電所１、２号機 アスファルト固化建屋における火災]]></TITLE_NAME>
	<UNITS><![CDATA[1,2]]></UNITS>
	<ATTACH_UMU_CODE><![CDATA[1]]></ATTACH_UMU_CODE>
	<ATTACH_UMU_CODE_NAME><![CDATA[あり]]></ATTACH_UMU_CODE_NAME>
	<KOKAI_FLG><![CDATA[1]]></KOKAI_FLG>
	<FIRST_KOKAI_DATE><![CDATA[2022/02/03 14:39:47]]></FIRST_KOKAI_DATE>
	<COM_COMPANY>
		<COMPANY_NAME><![CDATA[関西電力]]></COMPANY_NAME>
		<COMPANY_SHORT_NAME><![CDATA[関西]]></COMPANY_SHORT_NAME>
		<COMPANY_FULL_NAME><![CDATA[関西電力株式会社]]></COMPANY_FULL_NAME>
		<CREATE_DATE><![CDATA[2010/05/31 00:00:00]]></CREATE_DATE>
		<COMPANY_CODE><![CDATA[kns]]></COMPANY_CODE>
		<CREATE_USER_CODE><![CDATA[mainte01]]></CREATE_USER_CODE>
		<SORT_NO>60</SORT_NO>
		<SYSTEM_CODE><![CDATA[KN]]></SYSTEM_CODE>
		<D_RO_TYPE_CODE><![CDATA[P]]></D_RO_TYPE_CODE>
	</COM_COMPANY>
	<KNM_PLANT>
		<COMPANY_CODE><![CDATA[kns]]></COMPANY_CODE>
		<CREATE_USER_CODE><![CDATA[mainte01]]></CREATE_USER_CODE>
		<PLANT_RYAKU_NAME><![CDATA[高浜]]></PLANT_RYAKU_NAME>
		<SORT_NO>11</SORT_NO>
		<PLANT_CODE><![CDATA[knsth]]></PLANT_CODE>
		<D_RO_TYPE_CODE><![CDATA[P]]></D_RO_TYPE_CODE>
		<PLANT_NAME><![CDATA[高浜発電所]]></PLANT_NAME>
		<CREATE_DATE><![CDATA[2010/05/31 00:00:00]]></CREATE_DATE>
	</KNM_PLANT>
</KNT_TROUBLE>
