<?xml version="1.0" encoding="UTF-8" standalone="yes"?>
<KNT_TROUBLE>
	<KOKAI_REV_NBR>1</KOKAI_REV_NBR>
	<TROUBLE_ID>12906</TROUBLE_ID>
	<KANRYO_FLG><![CDATA[0]]></KANRYO_FLG>
	<UPDATE_DATE><![CDATA[2019/01/23 11:36:16]]></UPDATE_DATE>
	<JOHO_KUBUN_CODE><![CDATA[S]]></JOHO_KUBUN_CODE>
	<JOHO_KUBUN_CODE_NAME><![CDATA[その他情報]]></JOHO_KUBUN_CODE_NAME>
	<RO_TYPE_CODE><![CDATA[B]]></RO_TYPE_CODE>
	<RO_TYPE_CODE_NAME><![CDATA[BWR]]></RO_TYPE_CODE_NAME>
	<SUIHEI_KENTO_CODE><![CDATA[X]]></SUIHEI_KENTO_CODE>
	<SUIHEI_KENTO_CODE_NAME><![CDATA[対象外]]></SUIHEI_KENTO_CODE_NAME>
	<CREATE_DATE><![CDATA[2019/01/09 10:19:21]]></CREATE_DATE>
	<HASSEI_NJ><![CDATA[201811281527]]></HASSEI_NJ>
	<KOKAI_UPDATE_DATE><![CDATA[2019/01/23 11:36:16]]></KOKAI_UPDATE_DATE>
	<HASSEIJI_JOKYO_TXT><![CDATA[　２０１８年１１月２８日１５時２４分に原子炉建屋（管理区域内）地下２階のストームドレンサンプ※１ポンプ（Ｃ）を中央制御室より起動※２した。
　その後，１５時２７分に現場にいた運転員が当該ポンプ軸封部※３より白い煙らしきものを確認するとともに焦げ臭い匂いを確認したため，中央制御室に連絡した。
　中央制御室の運転員は１５時２７分，直ちに当該ポンプを停止した。これに伴い白い煙らしきものはなくなった。
　発電長は速やかに公設消防に１１９番通報した（公設消防の覚知時刻１５時３９分）。また，１５時３２分に当該ポンプの隔離措置（操作スイッチ，電源，出口弁）を完了した。
　公設消防は，１５時５５分に発電所へ到着し，現場の状況確認を開始した。その結果，１６時２２分に公設消防により「本事象は火災ではない」と判断された。

　※１：原子炉建屋内で排水される海水等が集水される水溜め
　※２：当該サンプの水位高低検知用スイッチの点検終了に伴う試運転のため起動した。
　※３：ポンプ軸より排水が漏れ出ないようにするための押え（通称：グランドパッキング）]]></HASSEIJI_JOKYO_TXT>
	<PLANT_CODE><![CDATA[gentk]]></PLANT_CODE>
	<REPORT_NO><![CDATA[2018-原電-S001]]></REPORT_NO>
	<COMPANY_CODE><![CDATA[gen]]></COMPANY_CODE>
	<HOKOKUSHO_JOTAI_CODE><![CDATA[02]]></HOKOKUSHO_JOTAI_CODE>
	<HOKOKUSHO_JOTAI_CODE_NAME><![CDATA[最終報告]]></HOKOKUSHO_JOTAI_CODE_NAME>
	<TITLE_NAME><![CDATA[原子炉建屋ストームドレンサンプポンプ（C)軸封部からの煙らしきものの確認]]></TITLE_NAME>
	<ATTACH_UMU_CODE><![CDATA[2]]></ATTACH_UMU_CODE>
	<ATTACH_UMU_CODE_NAME><![CDATA[なし]]></ATTACH_UMU_CODE_NAME>
	<KOKAI_FLG><![CDATA[1]]></KOKAI_FLG>
	<FIRST_KOKAI_DATE><![CDATA[2019/01/09 10:19:45]]></FIRST_KOKAI_DATE>
	<COM_COMPANY>
		<COMPANY_NAME><![CDATA[日本原子力発電]]></COMPANY_NAME>
		<COMPANY_SHORT_NAME><![CDATA[原電]]></COMPANY_SHORT_NAME>
		<COMPANY_FULL_NAME><![CDATA[日本原子力発電株式会社]]></COMPANY_FULL_NAME>
		<CREATE_DATE><![CDATA[2010/05/31 00:00:00]]></CREATE_DATE>
		<COMPANY_CODE><![CDATA[gen]]></COMPANY_CODE>
		<CREATE_USER_CODE><![CDATA[mainte01]]></CREATE_USER_CODE>
		<SORT_NO>100</SORT_NO>
		<SYSTEM_CODE><![CDATA[KN]]></SYSTEM_CODE>
		<D_RO_TYPE_CODE><![CDATA[B]]></D_RO_TYPE_CODE>
	</COM_COMPANY>
	<KNM_PLANT>
		<COMPANY_CODE><![CDATA[gen]]></COMPANY_CODE>
		<CREATE_USER_CODE><![CDATA[mainte01]]></CREATE_USER_CODE>
		<PLANT_RYAKU_NAME><![CDATA[東海第二]]></PLANT_RYAKU_NAME>
		<SORT_NO>17</SORT_NO>
		<PLANT_CODE><![CDATA[gentk]]></PLANT_CODE>
		<D_RO_TYPE_CODE><![CDATA[B]]></D_RO_TYPE_CODE>
		<PLANT_NAME><![CDATA[東海第二発電所]]></PLANT_NAME>
		<CREATE_DATE><![CDATA[2010/05/31 00:00:00]]></CREATE_DATE>
	</KNM_PLANT>
</KNT_TROUBLE>
