<?xml version="1.0" encoding="UTF-8" standalone="yes"?>
<KNT_TROUBLE>
	<KOKAI_REV_NBR>1</KOKAI_REV_NBR>
	<TROUBLE_ID>12057</TROUBLE_ID>
	<KANRYO_FLG><![CDATA[0]]></KANRYO_FLG>
	<UPDATE_DATE><![CDATA[2015/12/22 23:40:51]]></UPDATE_DATE>
	<JOHO_KUBUN_CODE><![CDATA[S]]></JOHO_KUBUN_CODE>
	<JOHO_KUBUN_CODE_NAME><![CDATA[その他情報]]></JOHO_KUBUN_CODE_NAME>
	<RO_TYPE_CODE><![CDATA[B]]></RO_TYPE_CODE>
	<RO_TYPE_CODE_NAME><![CDATA[BWR]]></RO_TYPE_CODE_NAME>
	<SUIHEI_KENTO_CODE><![CDATA[X]]></SUIHEI_KENTO_CODE>
	<SUIHEI_KENTO_CODE_NAME><![CDATA[対象外]]></SUIHEI_KENTO_CODE_NAME>
	<ATTACH_ID>59097</ATTACH_ID>
	<CREATE_DATE><![CDATA[2014/06/09 22:14:52]]></CREATE_DATE>
	<HASSEI_NJ><![CDATA[201406060830]]></HASSEI_NJ>
	<KOKAI_UPDATE_DATE><![CDATA[2015/12/22 23:40:51]]></KOKAI_UPDATE_DATE>
	<HASSEIJI_JOKYO_TXT><![CDATA[６月６日午前８時30分頃、構内登録センター西側道路上において、協力企業が使用している車両の燃料配管より油漏れ（ガソリン）を発見。車両のエンジンを停止したところ、漏えいは停止。漏えいしたガソリンは、コンクリート床面に約３ｍ×約１ｍの範囲で溜まっていることから、受け皿を設置し、漏えい箇所は吸着マットおよび中和剤により処置を実施。なお、同日午前８時53分に一般回線にて双葉消防本部へ連絡。同日午前10時29分に双葉消防本部より「危険物の漏えい事象」との判断を受けた。その後、同日午後２時10分に漏えいしたガソリンの回収作業を終了。漏えい原因を調査した結果、車両走行時に道路脇の側溝上を通過した際、側溝のグレーチング蓋が跳ね上がり車両下部に接触したことにより、燃料配管が損傷したものと推定。]]></HASSEIJI_JOKYO_TXT>
	<PLANT_CODE><![CDATA[tyo1f]]></PLANT_CODE>
	<REPORT_NO><![CDATA[2014-東京-S026]]></REPORT_NO>
	<COMPANY_CODE><![CDATA[tyo]]></COMPANY_CODE>
	<HOKOKUSHO_JOTAI_CODE><![CDATA[02]]></HOKOKUSHO_JOTAI_CODE>
	<HOKOKUSHO_JOTAI_CODE_NAME><![CDATA[最終報告]]></HOKOKUSHO_JOTAI_CODE_NAME>
	<TITLE_NAME><![CDATA[福島第一原子力発電所　構内道路上における車両の油漏れについて]]></TITLE_NAME>
	<ATTACH_UMU_CODE><![CDATA[1]]></ATTACH_UMU_CODE>
	<ATTACH_UMU_CODE_NAME><![CDATA[あり]]></ATTACH_UMU_CODE_NAME>
	<KOKAI_FLG><![CDATA[1]]></KOKAI_FLG>
	<FIRST_KOKAI_DATE><![CDATA[2014/06/12 13:23:51]]></FIRST_KOKAI_DATE>
	<COM_COMPANY>
		<COMPANY_NAME><![CDATA[東京電力]]></COMPANY_NAME>
		<COMPANY_SHORT_NAME><![CDATA[東京]]></COMPANY_SHORT_NAME>
		<COMPANY_FULL_NAME><![CDATA[東京電力株式会社]]></COMPANY_FULL_NAME>
		<CREATE_DATE><![CDATA[2010/05/31 00:00:00]]></CREATE_DATE>
		<COMPANY_CODE><![CDATA[tyo]]></COMPANY_CODE>
		<CREATE_USER_CODE><![CDATA[mainte01]]></CREATE_USER_CODE>
		<SORT_NO>30</SORT_NO>
		<SYSTEM_CODE><![CDATA[KN]]></SYSTEM_CODE>
		<D_RO_TYPE_CODE><![CDATA[B]]></D_RO_TYPE_CODE>
	</COM_COMPANY>
	<KNM_PLANT>
		<COMPANY_CODE><![CDATA[tyo]]></COMPANY_CODE>
		<CREATE_USER_CODE><![CDATA[mainte01]]></CREATE_USER_CODE>
		<PLANT_RYAKU_NAME><![CDATA[福島第一]]></PLANT_RYAKU_NAME>
		<SORT_NO>4</SORT_NO>
		<PLANT_CODE><![CDATA[tyo1f]]></PLANT_CODE>
		<D_RO_TYPE_CODE><![CDATA[B]]></D_RO_TYPE_CODE>
		<PLANT_NAME><![CDATA[福島第一発電所]]></PLANT_NAME>
		<CREATE_DATE><![CDATA[2010/05/31 00:00:00]]></CREATE_DATE>
	</KNM_PLANT>
</KNT_TROUBLE>
