<?xml version="1.0" encoding="UTF-8" standalone="yes"?>
<KNT_TROUBLE>
	<CHOSA_GAIYO_TXT><![CDATA[（１）外観点検
　床ドレン受タンク循環配管及び廃液濃縮器供給ポンプＤ入口配管について、目視による外観点検を実施した結果、今回にじみが確認されたエルボ部と直管部（以下「Ｗ２」※という。）の他、Ｔ字管とエルボ部との溶接部（以下「Ｗ３」※という。）ににじみ跡、Ｔ字管とレジューサとの溶接部（以下「Ｗ４」※という。）に腐食と思われる跡を確認した。
　なお、今回にじみが確認された箇所と同時期に取替えた床ドレン受タンク循環配管については、外観点検の結果、異常は見られなかった。

※Ｗ２，３，４：溶接箇所の溶接番号をいう

（２）内面点検
　床ドレン受タンク循環配管及び廃液濃縮器供給ポンプＤ入口配管について、内面目視観察を実施した結果、Ｗ２，Ｗ３の内面は、全体的に裏波ビードが均一ではなく、へこみ、垂れ込みが確認された。へこみ量は深さ約０.９ミリ程度、垂れ込み量は内表面からの高さ約２ミリ程度であった。溶接部Ｗ４の内面の裏波ビードは正常に形成されていた。また、エロージョン及び減肉は確認されなかった。

（３）浸透探傷試験（ＰＴ）
　床ドレン受タンク循環配管及び廃液濃縮器供給ポンプＤ入口配管について、浸透探傷試験（ＰＴ）を実施した結果、Ｗ２にφ０.５ミリ（２箇所）、φ１.０ミリ、Ｗ３に２.０ミリ×１.０ミリ、φ１.０ミリ、Ｗ４にφ０.５ミリ以下の円形状指示模様を確認したが、割れ等はなかった。尚、指示模様はすべて判定基準を満足するものであった。

（４）放射線透過試験（ＲＴ）
　にじみが確認された床ドレン受タンク循環配管について、放射線透過試験（ＲＴ）を実施し、内部状況を確認した結果、Ｗ２，Ｗ３に配管外表面で指示模様が確認された箇所及びその他の部位に欠陥模様が確認された。

（５）電子顕微鏡（ＳＥＭ）観察
　床ドレン受タンク循環配管及び廃液濃縮器供給ポンプＤ入口配管について、電子顕微鏡（ＳＥＭ）観察を実施した結果は以下のとおりであった。
a.外表面ＳＥＭ観察結果
　Ｗ２，Ｗ３の浸透探傷試験で指示模様が確認された箇所に腐食跡、穴を確認した。なお、割れ状の欠陥はなかった。Ｗ３外面には、くぼみと思われる箇所が確認された。また、Ｗ４部には、軽微な腐食跡を確認した。
b.内表面ＳＥＭ観察結果
　Ｗ２に腐食による貫通した腐食跡、穴を確認した。Ｗ３には、腐食跡を確認した。Ｗ４には腐食による穴を確認した。なお、いずれも割れ状の欠陥はなかった。また、Ｗ３内面に溶接の溶け込み不良と思われる箇所が確認された。
c.断面観察結果
　溶接部Ｗ２，Ｗ３に腐食による貫通した腐食跡を確認した。また、Ｗ３外表面に溶接欠陥（アンダカット）と思われる箇所、内表面に溶接の溶け込み不良と思われる箇所が確認された。Ｗ４部内表面には軽微な腐食跡を確認したが貫通は認められなかった。また、板厚方向に約０.１６ミリの深さの製造時の欠陥と思われる模様が確認された。この欠陥は、浸透探傷試験の結果、判定基準内であり、深さ方向もわずかであることから配管の健全性に問題はなかったと考えられる。

（６）付着物調査・堆積物確認
 床ドレン受タンク循環配管及び廃液濃縮器供給ポンプＤ入口配管について、配管内外面の付着物調査を実施した結果、配管の外面の塩分付着量は、最大で１４．０ミリグラムCl/m2であり、メーカ管理値７０ミリグラムCl/m2に比べ十分低い値であり、外面からの塩分による影響はないと推察された。また、配管内面の成分分析の結果、ステンレス鋼成分以外にＣｌ（塩素）が確認された。内表面に確認された塩素の濃度は、分析装置の検出限界から３０００ppm以上あると考えられる。
 また、床ドレン受タンクの水質調査結果より廃液中には塩素が含まれていることが確認されている。
堆積物確認では、床ドレン受タンク循環配管及び廃液濃縮器供給ポンプＤ入口配管について、堆積物確認を実施した結果、配管内部の底部に堆積物があることが確認された。なお、堆積物は、通常処理ルートの直管部より、通常処理ルートから分岐しているエルボ部の方が多く、また直管部では、レジューサ下流側より上流側に多く堆積していることが確認された。

（７）配管素材確認、溶接施工記録確認
 床ドレン受タンク循環配管及び廃液濃縮器供給ポンプＤ入口配管について、配管素材及び溶接施工記録を確認した結果、配管材、ミルシートの化学成分、機械的性質は、すべて規格
値内であった。また、溶接施工記録、検査記録を確認し、問題のないことを確認した。
全体的に裏波ビードが均一ではなく、へこみ、垂れ込みが確認されたＷ２，Ｗ３については、現地溶接施工（新廃棄物処理建屋地下）であり、内面の裏波ビードが正常に形成されていたＷ４部は、工場で内作していたことを確認した。
聞き取りの結果、平成２０年４月に行われた床ドレン受タンク循環配管取替の際、既設配管と同様の布設ルート及び同様な溶接箇所で作業を行うことを計画したため、現地で配管合わせし、現地溶接した箇所が多くなっていたことを確認した。Ｗ２、Ｗ３溶接部は、現地で配管合わせ、溶接した箇所であり、他の溶接箇所の場所にくらべ狭隘な作業環境であった。

３．現場状況確認
（１）にじみや、配管の腐食が確認された箇所は、通常処理ルートから分岐した箇所やレジューサ上流の流速が遅い箇所であり、系統上廃液が滞留し易い箇所であった。
（２）現地溶接を行ったＷ２，Ｗ３は配管下部に別の配管等が布設されている狭隘部であることから、溶接しにくい箇所であった。

４．運転状況確認結果
（１）床ドレン受タンク循環配管は、タンク水のサンプリングが必要となった場合、循環ポンプを運転するために設置されているが、通常、上流側のタンク（床ドレン収集タンク）にてサンプリングを行っていることから、床ドレン受タンク循環配管は使用していない。
 なお、上流側タンク（床ドレン収集タンク）でサンプリングが出来ない場合、また、床ドレン受タンクの高濃度廃液を受入れた場合、床ドレン受タンク循環配管を使用し、サンプリングを行うが、平成２０年４月に行われた床ドレン受タンク循環配管を取替後、作業に伴う循環運転を含め、５回しか当該配管を使用していない状況であり、平成２１年３月９日以降、当該配管を使用していないことを確認した。

５．調査結果のまとめ
（１）電子顕微鏡（ＳＥＭ）による内面及び断面観察の結果、Ｗ２，Ｗ３に腐食による貫通した腐食跡が確認されたが、割れ状の欠陥はなかった。
（２）Ｗ２，Ｗ３の内面は、裏波部にへこみ、垂れ込みなどの形状不良が確認されており、スラッジが堆積し易く腐食発生の起点となる可能性があった。これは、Ｗ２，Ｗ３の配管下部に別の配管等が布設されている狭隘部であったことから溶接不良になったと推定される。
（３）付着物成分分析をした結果、ステンレス鋼成分以外に塩素が確認された。
（４）にじみや、配管の腐食が確認された箇所は、通常処理ルートから分岐した箇所やレジューサ上流の流速が遅い箇所であり、系統上廃液が滞留し易い箇所であった。
（５）配管の内部は、底部に堆積物が確認された。堆積物は、通常処理ルートの直管部より、通常処理ルートから分岐しているエルボ部の方が多く、また直管部では、レジューサ下流側より上流側に多く堆積していることが確認された。

]]></CHOSA_GAIYO_TXT>
	<PLANT_EIKYO_TXT><![CDATA[]]></PLANT_EIKYO_TXT>
	<SEIGENGAI_UMU_CODE><![CDATA[2]]></SEIGENGAI_UMU_CODE>
	<SEIGENGAI_UMU_CODE_NAME><![CDATA[なし]]></SEIGENGAI_UMU_CODE_NAME>
	<PLANT_EIKYO_UMU_CODE><![CDATA[2]]></PLANT_EIKYO_UMU_CODE>
	<PLANT_EIKYO_UMU_CODE_NAME><![CDATA[なし]]></PLANT_EIKYO_UMU_CODE_NAME>
	<KOKAI_REV_NBR>0</KOKAI_REV_NBR>
	<KEITO_CODE><![CDATA[141]]></KEITO_CODE>
	<SETSUBI_CODE><![CDATA[09]]></SETSUBI_CODE>
	<KITEI_IHAN_UMU_CODE><![CDATA[2]]></KITEI_IHAN_UMU_CODE>
	<KITEI_IHAN_UMU_CODE_NAME><![CDATA[なし]]></KITEI_IHAN_UMU_CODE_NAME>
	<TROUBLE_ID>10609</TROUBLE_ID>
	<HAKKEN_HOHO_CODE><![CDATA[03]]></HAKKEN_HOHO_CODE>
	<HAKKEN_HOHO_CODE_NAME><![CDATA[運転操作]]></HAKKEN_HOHO_CODE_NAME>
	<UNTEN_MODE_CODE><![CDATA[105]]></UNTEN_MODE_CODE>
	<UNTEN_MODE_CODE_NAME><![CDATA[燃料交換]]></UNTEN_MODE_CODE_NAME>
	<INES_CODE><![CDATA[N]]></INES_CODE>
	<INES_CODE_NAME><![CDATA[評価不要]]></INES_CODE_NAME>
	<UPDATE_DATE><![CDATA[2009/12/28 13:12:31]]></UPDATE_DATE>
	<JOHO_KUBUN_CODE><![CDATA[M]]></JOHO_KUBUN_CODE>
	<JOHO_KUBUN_CODE_NAME><![CDATA[保全品質情報]]></JOHO_KUBUN_CODE_NAME>
	<SEIGENGAI_TXT><![CDATA[]]></SEIGENGAI_TXT>
	<RO_TYPE_CODE><![CDATA[B]]></RO_TYPE_CODE>
	<RO_TYPE_CODE_NAME><![CDATA[BWR]]></RO_TYPE_CODE_NAME>
	<SUIHEI_KENTO_CODE><![CDATA[1]]></SUIHEI_KENTO_CODE>
	<SUIHEI_KENTO_CODE_NAME><![CDATA[要]]></SUIHEI_KENTO_CODE_NAME>
	<HOSHANO_EIKYO_UMU_CODE><![CDATA[2]]></HOSHANO_EIKYO_UMU_CODE>
	<HOSHANO_EIKYO_UMU_CODE_NAME><![CDATA[なし]]></HOSHANO_EIKYO_UMU_CODE_NAME>
	<ATTACH_ID>4578</ATTACH_ID>
	<CREATE_DATE><![CDATA[2009/10/06 16:33:30]]></CREATE_DATE>
	<HASSEI_NJ><![CDATA[20090731]]></HASSEI_NJ>
	<SB_TAISAKU_TXT><![CDATA[・短期的な対策
（１）循環配管のにじみ等が認められた箇所については、既設と同材料（ステンレス鋼）のものに取替えを行う。なお、溶接においては、へこみ、垂れ込みが発生しないよう、工場での溶接施工を極力実施し、現地溶接箇所については、干渉物のない箇所に溶接線を計画することとする。なお、現地溶接に当っては事前にモックアップを行うこととする。
（２）現地溶接した箇所については、溶接状態を検証するため、放射線透過検査（ＲＴ）を行うこととする。
（３）床ドレン系及び高電導度ドレン系において、廃液が滞留し易い箇所については、定期的な循環運転及びフラッシングを実施し、滞留を防止するよう運転管理を変更する。
（４）にじみ等が確認された配管と同様に廃液が滞留し易い箇所について、運転圧力以上での漏えい確認等により外観状況を確認し、今後の対策を実施するまでの間、補修材にて補強を行う。

・今後の対策
　推定原因より、今回の事象は、ステンレス鋼配管内の溶接形状の不良箇所等にスラッジが堆積し隙間部で塩化物イオンが濃縮し腐食が進行したことから、事象発生の可能性があるステンレス鋼配管を使用している床ドレン受タンク循環配管及び床ドレン受タンクから廃液濃縮器廃液入口弁までの配管について以下のとおり検討し、恒久対策を実施する。
（１）スラッジ清掃
　定期的な循環運転及びフラッシングを継続するとともに、平成２１年度中に床ドレン受タンク内を清掃し、配管内及びタンク内にあるスラッジを除去し、スラッジ堆積による配管の腐食発生防止を図る。また、今回取替えた箇所の腐食の有無について定期的に放射線透過検査（ＲＴ）にて確認し、スラッジ清掃の効果を確認する。
　以降、床ドレン受タンクは定期的な清掃を計画する。
（２）配管取替
　床ドレン受タンク循環配管及び床ドレン受タンクから廃液濃縮器廃液入口弁までの配管の取替え計画を検討する。計画に当っては、内面にライニングした配管への取替、または、既設のＳＵＳ３０４から、より耐食性に優れた材料への変更を検討する。
]]></SB_TAISAKU_TXT>
	<AUTO_ANZEN_UMU_CODE><![CDATA[2]]></AUTO_ANZEN_UMU_CODE>
	<AUTO_ANZEN_UMU_CODE_NAME><![CDATA[なし]]></AUTO_ANZEN_UMU_CODE_NAME>
	<SONOTA_TXT><![CDATA[]]></SONOTA_TXT>
	<KOKAI_UPDATE_DATE><![CDATA[2009/12/28 13:12:31]]></KOKAI_UPDATE_DATE>
	<HASSEIJI_JOKYO_TXT><![CDATA[　敦賀発電所１号機は、第３２回定期検査中のところ、平成２１年７月３１日０時５０分頃、新廃棄物処理建屋地下１階にて、廃液濃縮器Ｄにて廃液を処理する準備として、廃液濃縮器Ｄ供給ポンプ起動後の運転状況を確認していた運転員が、廃液濃縮器Ｃ、Ｄ供給ポンプ室に敷設されている床ドレン受タンク出口循環配管の下部床面に約２ｃｍ四方の滴下跡を発見した。
　滴下跡部では放射能は検出されなかった。
　床ドレン受タンク出口循環配管の外観を点検したところ、同配管のエルボ部に水滴が付着していたことから、この水滴を拭取り、配管からの漏れの有無を確認した結果、同配管のエルボ部と直管部との溶接部付近からにじみを確認した。
]]></HASSEIJI_JOKYO_TXT>
	<TEISHI_CHU_FLG><![CDATA[0]]></TEISHI_CHU_FLG>
	<PLANT_CODE><![CDATA[gentu]]></PLANT_CODE>
	<REPORT_NO><![CDATA[2009-原電-M010]]></REPORT_NO>
	<COMPANY_CODE><![CDATA[gen]]></COMPANY_CODE>
	<JISHO_GENIN_TXT><![CDATA[ 床ドレン受タンク内の廃液には湧水が含まれており、床ドレン受タンク水の分析結果から塩素が確認されている。
にじみ箇所は、通常処理ルートから分岐している箇所であり、系統上廃液が滞留し易いステンレス鋼配管の箇所であること。且つ、狭隘な作業環境で現地溶接施工した箇所で溶接形状が不良となった箇所であり、スラッジ等が堆積し、腐食が発生し易い環境であった。
また、腐食跡が確認された箇所は、ステンレス鋼のレジューサ部であり、配管径が絞られていることから、流速が遅い箇所にスラッジ等が堆積し、腐食が発生し易い環境であった。
よって、溶接形状の不良箇所等にスラッジが堆積したことにより生じた隙間部において、廃液中に含まれる塩化物イオンが濃縮し、ステンレスの不動態皮膜が損傷し腐食が進展したと推定される。
]]></JISHO_GENIN_TXT>
	<HOKOKUSHO_JOTAI_CODE><![CDATA[02]]></HOKOKUSHO_JOTAI_CODE>
	<HOKOKUSHO_JOTAI_CODE_NAME><![CDATA[最終報告]]></HOKOKUSHO_JOTAI_CODE_NAME>
	<HOSHANO_EIKYO_TXT><![CDATA[]]></HOSHANO_EIKYO_TXT>
	<TITLE_NAME><![CDATA[敦賀発電所１号機　床ドレン受タンク出口循環配管からのにじみについて]]></TITLE_NAME>
	<IHAN_SHOSAI_TXT><![CDATA[]]></IHAN_SHOSAI_TXT>
	<UNITS><![CDATA[1]]></UNITS>
	<ATTACH_UMU_CODE><![CDATA[1]]></ATTACH_UMU_CODE>
	<ATTACH_UMU_CODE_NAME><![CDATA[あり]]></ATTACH_UMU_CODE_NAME>
	<DENKI_OUTPUT_NBR>0</DENKI_OUTPUT_NBR>
	<MANUAL_ANZEN_UMU_CODE><![CDATA[2]]></MANUAL_ANZEN_UMU_CODE>
	<MANUAL_ANZEN_UMU_CODE_NAME><![CDATA[なし]]></MANUAL_ANZEN_UMU_CODE_NAME>
	<KOKAI_FLG><![CDATA[1]]></KOKAI_FLG>
	<FIRST_KOKAI_DATE><![CDATA[2009/10/13 11:51:00]]></FIRST_KOKAI_DATE>
	<KNM_PLANT>
		<COMPANY_CODE><![CDATA[gen]]></COMPANY_CODE>
		<CREATE_USER_CODE><![CDATA[mainte01]]></CREATE_USER_CODE>
		<PLANT_RYAKU_NAME><![CDATA[敦賀]]></PLANT_RYAKU_NAME>
		<SORT_NO>18</SORT_NO>
		<PLANT_CODE><![CDATA[gentu]]></PLANT_CODE>
		<D_RO_TYPE_CODE><![CDATA[B]]></D_RO_TYPE_CODE>
		<PLANT_NAME><![CDATA[敦賀発電所]]></PLANT_NAME>
		<CREATE_DATE><![CDATA[2010/05/31 00:00:00]]></CREATE_DATE>
	</KNM_PLANT>
	<G_KNT_SUIHEI>
		<KNT_SUIHEI>
			<DISP_NO><![CDATA[a]]></DISP_NO>
			<TROUBLE_ID>10609</TROUBLE_ID>
			<SUIHEI_SEQ_NBR>1</SUIHEI_SEQ_NBR>
		</KNT_SUIHEI>
		<KNT_SUIHEI>
			<DISP_NO><![CDATA[b]]></DISP_NO>
			<TROUBLE_ID>10609</TROUBLE_ID>
			<SUIHEI_SEQ_NBR>2</SUIHEI_SEQ_NBR>
		</KNT_SUIHEI>
		<KNT_SUIHEI>
			<DISP_NO><![CDATA[c]]></DISP_NO>
			<TROUBLE_ID>10609</TROUBLE_ID>
			<SUIHEI_SEQ_NBR>3</SUIHEI_SEQ_NBR>
		</KNT_SUIHEI>
		<KNT_SUIHEI>
			<DISP_NO><![CDATA[d]]></DISP_NO>
			<TROUBLE_ID>10609</TROUBLE_ID>
			<SUIHEI_SEQ_NBR>4</SUIHEI_SEQ_NBR>
		</KNT_SUIHEI>
		<KNT_SUIHEI>
			<DISP_NO><![CDATA[e]]></DISP_NO>
			<TROUBLE_ID>10609</TROUBLE_ID>
			<SUIHEI_SEQ_NBR>5</SUIHEI_SEQ_NBR>
		</KNT_SUIHEI>
	</G_KNT_SUIHEI>
	<G_KNT_KIKI>
		<KNT_KIKI>
			<KIKI_CODE><![CDATA[511]]></KIKI_CODE>
			<TROUBLE_ID>10609</TROUBLE_ID>
			<KIKI_SEQ_NBR>1</KIKI_SEQ_NBR>
			<G_KNT_KIKI_BUHIN>
				<KNT_KIKI_BUHIN>
					<BUHIN_SEQ_NBR>1</BUHIN_SEQ_NBR>
					<S_BUHIN_NAME><![CDATA[配管*]]></S_BUHIN_NAME>
					<TROUBLE_ID>10609</TROUBLE_ID>
					<BUHIN_CODE><![CDATA[999]]></BUHIN_CODE>
					<KIKI_SEQ_NBR>1</KIKI_SEQ_NBR>
					<KNM_BUHIN>
						<BUHIN_NAME><![CDATA[その他]]></BUHIN_NAME>
						<INPUT_TYPE_CODE><![CDATA[1]]></INPUT_TYPE_CODE>
						<INPUT_TYPE_CODE_NAME><![CDATA[その他]]></INPUT_TYPE_CODE_NAME>
						<CREATE_USER_CODE><![CDATA[mainte01]]></CREATE_USER_CODE>
						<SORT_NO>150</SORT_NO>
						<BUHIN_CODE><![CDATA[999]]></BUHIN_CODE>
						<CREATE_DATE><![CDATA[2010/05/31 00:00:00]]></CREATE_DATE>
					</KNM_BUHIN>
				</KNT_KIKI_BUHIN>
			</G_KNT_KIKI_BUHIN>
			<KNM_KIKI>
				<KIKI_CODE><![CDATA[511]]></KIKI_CODE>
				<INPUT_TYPE_CODE><![CDATA[0]]></INPUT_TYPE_CODE>
				<INPUT_TYPE_CODE_NAME><![CDATA[その他/不明不選択]]></INPUT_TYPE_CODE_NAME>
				<CREATE_USER_CODE><![CDATA[mainte01]]></CREATE_USER_CODE>
				<KIKI_NAME><![CDATA[配管（計装配管・オリフィス本体除く）]]></KIKI_NAME>
				<SORT_NO>1</SORT_NO>
				<OYA_KIKI_CODE><![CDATA[510]]></OYA_KIKI_CODE>
				<CREATE_DATE><![CDATA[2010/05/31 00:00:00]]></CREATE_DATE>
				<KNM_KIKI>
					<KIKI_CODE><![CDATA[510]]></KIKI_CODE>
					<INPUT_TYPE_CODE><![CDATA[0]]></INPUT_TYPE_CODE>
					<INPUT_TYPE_CODE_NAME><![CDATA[その他/不明不選択]]></INPUT_TYPE_CODE_NAME>
					<CREATE_USER_CODE><![CDATA[mainte01]]></CREATE_USER_CODE>
					<KIKI_NAME><![CDATA[配管装置]]></KIKI_NAME>
					<SORT_NO>31</SORT_NO>
					<CREATE_DATE><![CDATA[2010/05/31 00:00:00]]></CREATE_DATE>
				</KNM_KIKI>
			</KNM_KIKI>
		</KNT_KIKI>
	</G_KNT_KIKI>
	<KNM_KEITO>
		<KEITO_NAME><![CDATA[液体廃棄物処理系]]></KEITO_NAME>
		<INPUT_TYPE_CODE><![CDATA[0]]></INPUT_TYPE_CODE>
		<INPUT_TYPE_CODE_NAME><![CDATA[その他/不明不選択]]></INPUT_TYPE_CODE_NAME>
		<CREATE_USER_CODE><![CDATA[mainte01]]></CREATE_USER_CODE>
		<HYOJUN_KEITO_CODE><![CDATA[141]]></HYOJUN_KEITO_CODE>
		<KEITO_CODE><![CDATA[141]]></KEITO_CODE>
		<CREATE_DATE><![CDATA[2010/05/31 00:00:00]]></CREATE_DATE>
	</KNM_KEITO>
	<G_KNT_GENIN>
		<KNT_GENIN>
			<TROUBLE_ID>10609</TROUBLE_ID>
			<OLD_NEW_KUBUN_CODE><![CDATA[O]]></OLD_NEW_KUBUN_CODE>
			<OLD_NEW_KUBUN_CODE_NAME><![CDATA[旧区分]]></OLD_NEW_KUBUN_CODE_NAME>
			<GENIN_SHO_CODE><![CDATA[0620]]></GENIN_SHO_CODE>
			<SEQ_NBR>1</SEQ_NBR>
			<KNM_GENIN_SHO>
				<GENIN_SHO_NAME><![CDATA[化学腐しょく]]></GENIN_SHO_NAME>
				<INPUT_TYPE_CODE><![CDATA[0]]></INPUT_TYPE_CODE>
				<INPUT_TYPE_CODE_NAME><![CDATA[その他/不明不選択]]></INPUT_TYPE_CODE_NAME>
				<CREATE_USER_CODE><![CDATA[mainte01]]></CREATE_USER_CODE>
				<GENIN_DAI_CODE><![CDATA[060]]></GENIN_DAI_CODE>
				<SORT_NO>26</SORT_NO>
				<GENIN_SHO_CODE><![CDATA[0620]]></GENIN_SHO_CODE>
				<CREATE_DATE><![CDATA[2010/05/31 00:00:00]]></CREATE_DATE>
				<KNM_GENIN_DAI>
					<CREATE_USER_CODE><![CDATA[mainte01]]></CREATE_USER_CODE>
					<OLD_NEW_KUBUN_CODE><![CDATA[O]]></OLD_NEW_KUBUN_CODE>
					<OLD_NEW_KUBUN_CODE_NAME><![CDATA[旧区分]]></OLD_NEW_KUBUN_CODE_NAME>
					<GENIN_DAI_NAME><![CDATA[腐しょく]]></GENIN_DAI_NAME>
					<GENIN_DAI_CODE><![CDATA[060]]></GENIN_DAI_CODE>
					<SORT_NO>6</SORT_NO>
					<CREATE_DATE><![CDATA[2010/05/31 00:00:00]]></CREATE_DATE>
				</KNM_GENIN_DAI>
			</KNM_GENIN_SHO>
		</KNT_GENIN>
	</G_KNT_GENIN>
	<G_KNT_GENIN_SHUBETSU>
		<KNT_GENIN_SHUBETSU>
			<TROUBLE_ID>10609</TROUBLE_ID>
			<GENIN_SHUBETSU_CODE><![CDATA[AGING]]></GENIN_SHUBETSU_CODE>
			<GENIN_SHUBETSU_CODE_NAME><![CDATA[時間依存性]]></GENIN_SHUBETSU_CODE_NAME>
			<GENIN_SHUBETSU_UMU_CODE><![CDATA[2]]></GENIN_SHUBETSU_UMU_CODE>
			<GENIN_SHUBETSU_UMU_CODE_NAME><![CDATA[時間依存性のない事象（偶発事象を含む）]]></GENIN_SHUBETSU_UMU_CODE_NAME>
		</KNT_GENIN_SHUBETSU>
		<KNT_GENIN_SHUBETSU>
			<TROUBLE_ID>10609</TROUBLE_ID>
			<GENIN_SHUBETSU_CODE><![CDATA[FIRE]]></GENIN_SHUBETSU_CODE>
			<GENIN_SHUBETSU_CODE_NAME><![CDATA[火災]]></GENIN_SHUBETSU_CODE_NAME>
			<GENIN_SHUBETSU_UMU_CODE><![CDATA[2]]></GENIN_SHUBETSU_UMU_CODE>
			<GENIN_SHUBETSU_UMU_CODE_NAME><![CDATA[火災に該当しない事象]]></GENIN_SHUBETSU_UMU_CODE_NAME>
		</KNT_GENIN_SHUBETSU>
	</G_KNT_GENIN_SHUBETSU>
	<G_KNT_HOKOKU_KONKYO>
		<KNT_HOKOKU_KONKYO>
			<TROUBLE_ID>10609</TROUBLE_ID>
			<HOKOKU_KONKYO_CODE><![CDATA[198]]></HOKOKU_KONKYO_CODE>
			<HOKOKU_KONKYO_CODE_NAME><![CDATA[なし]]></HOKOKU_KONKYO_CODE_NAME>
			<SEQ_NBR>1</SEQ_NBR>
		</KNT_HOKOKU_KONKYO>
	</G_KNT_HOKOKU_KONKYO>
	<KNM_SETSUBI>
		<SETSUBI_CODE><![CDATA[09]]></SETSUBI_CODE>
		<INPUT_TYPE_CODE><![CDATA[0]]></INPUT_TYPE_CODE>
		<INPUT_TYPE_CODE_NAME><![CDATA[その他/不明不選択]]></INPUT_TYPE_CODE_NAME>
		<CREATE_USER_CODE><![CDATA[mainte01]]></CREATE_USER_CODE>
		<SETSUBI_NAME><![CDATA[廃棄設備]]></SETSUBI_NAME>
		<SORT_NO>9</SORT_NO>
		<CREATE_DATE><![CDATA[2010/05/31 00:00:00]]></CREATE_DATE>
	</KNM_SETSUBI>
	<COM_COMPANY>
		<COMPANY_NAME><![CDATA[日本原子力発電]]></COMPANY_NAME>
		<COMPANY_SHORT_NAME><![CDATA[原電]]></COMPANY_SHORT_NAME>
		<COMPANY_FULL_NAME><![CDATA[日本原子力発電株式会社]]></COMPANY_FULL_NAME>
		<CREATE_DATE><![CDATA[2010/05/31 00:00:00]]></CREATE_DATE>
		<COMPANY_CODE><![CDATA[gen]]></COMPANY_CODE>
		<CREATE_USER_CODE><![CDATA[mainte01]]></CREATE_USER_CODE>
		<SORT_NO>100</SORT_NO>
		<SYSTEM_CODE><![CDATA[KN]]></SYSTEM_CODE>
		<D_RO_TYPE_CODE><![CDATA[B]]></D_RO_TYPE_CODE>
	</COM_COMPANY>
</KNT_TROUBLE>
